{"date":"20260216","episode":"[5일간의 음악여행] 환상의 짝꿍","replayDuration":979,"songs":[{"songTitle":"그럴때마다","artist":"김연우Ψ김창원Ψ유희열Ψ윤종신Ψ이장우Ψ조규찬Ψ조삼희","musicId":"0000090005d280136c52","timestamp":"20260216220219","broadcastOffset":139,"songDuration":229,"talkTimeOffset":102.5,"refinedOffset":106.5,"refinementDelta":3.9,"matchMethod":"name","talkTimeBefore":139,"cumulativeSongDuration":0,"scriptMentions":[{"timestamp":97.6,"matchType":"title","matchedTerm":"그럴때마다"}]},{"songTitle":"LA VITA E BELLA","artist":"NICOLA PIOVANI","musicId":"0000090005d28019cfe0","timestamp":"20260216220923","broadcastOffset":563,"songDuration":166,"talkTimeOffset":246.4,"refinedOffset":246.4,"refinementDelta":0,"matchMethod":"talk_time","talkTimeBefore":334,"cumulativeSongDuration":229},{"songTitle":"기다린 날도 지워질 날도","artist":"이승환","musicId":"0000090005d28009b698","timestamp":"20260216221155","broadcastOffset":715,"songDuration":253,"talkTimeOffset":246.9,"refinedOffset":357.0,"refinementDelta":110.1,"matchMethod":"name","talkTimeBefore":320,"cumulativeSongDuration":395,"scriptMentions":[{"timestamp":245.6,"matchType":"artist","matchedTerm":"이승환"},{"timestamp":257.9,"matchType":"artist","matchedTerm":"이승환"},{"timestamp":260.4,"matchType":"title","matchedTerm":"기다린 날도 지워질 날도"},{"timestamp":268.9,"matchType":"artist","matchedTerm":"이승환"},{"timestamp":283.1,"matchType":"artist","matchedTerm":"이승환"},{"timestamp":301.3,"matchType":"artist","matchedTerm":"이승환"},{"timestamp":320.1,"matchType":"artist","matchedTerm":"이승환"},{"timestamp":341.7,"matchType":"artist","matchedTerm":"이승환"},{"timestamp":348.6,"matchType":"artist+title","matchedTerm":"이승환+기다린 날도 지워질 날도"}]},{"songTitle":"세상에 뿌려진 사랑만큼","artist":"이승환","musicId":"0000090005d2800ac60f","timestamp":"20260216221604","broadcastOffset":964,"songDuration":244,"talkTimeOffset":247.4,"refinedOffset":359.0,"refinementDelta":111.6,"matchMethod":"name","talkTimeBefore":316,"cumulativeSongDuration":648,"scriptMentions":[{"timestamp":245.6,"matchType":"artist","matchedTerm":"이승환"},{"timestamp":257.9,"matchType":"artist","matchedTerm":"이승환"},{"timestamp":268.9,"matchType":"artist","matchedTerm":"이승환"},{"timestamp":283.1,"matchType":"artist","matchedTerm":"이승환"},{"timestamp":295.2,"matchType":"title","matchedTerm":"세상에 뿌려진 사랑만큼"},{"timestamp":301.3,"matchType":"artist","matchedTerm":"이승환"},{"timestamp":320.1,"matchType":"artist","matchedTerm":"이승환"},{"timestamp":341.7,"matchType":"artist","matchedTerm":"이승환"},{"timestamp":348.6,"matchType":"artist+title","matchedTerm":"이승환+세상에 뿌려진 사랑만큼"}]},{"songTitle":"화려하지 않은 고백","artist":"이승환","musicId":"0000090005d2800b4ca7","timestamp":"20260216222034","broadcastOffset":1234,"songDuration":230,"talkTimeOffset":252.3,"refinedOffset":361.0,"refinementDelta":108.7,"matchMethod":"name","talkTimeBefore":342,"cumulativeSongDuration":892,"scriptMentions":[{"timestamp":245.6,"matchType":"artist","matchedTerm":"이승환"},{"timestamp":257.9,"matchType":"artist","matchedTerm":"이승환"},{"timestamp":268.9,"matchType":"artist","matchedTerm":"이승환"},{"timestamp":283.1,"matchType":"artist","matchedTerm":"이승환"},{"timestamp":295.2,"matchType":"title","matchedTerm":"화려하지 않은 고백"},{"timestamp":301.3,"matchType":"artist","matchedTerm":"이승환"},{"timestamp":320.1,"matchType":"artist","matchedTerm":"이승환"},{"timestamp":341.7,"matchType":"artist","matchedTerm":"이승환"},{"timestamp":348.6,"matchType":"artist+title","matchedTerm":"이승환+화려하지 않은 고백"}]},{"songTitle":"한사람을 위한 마음","artist":"이오공감","musicId":"0000090005d28007d927","timestamp":"20260216222352","broadcastOffset":1432,"songDuration":262,"talkTimeOffset":252.8,"refinedOffset":363.0,"refinementDelta":110.2,"matchMethod":"name","talkTimeBefore":310,"cumulativeSongDuration":1122,"scriptMentions":[{"timestamp":357.0,"matchType":"title","matchedTerm":"한사람을 위한 마음"}]},{"songTitle":"TO HEAVEN(천국으로 보낸 편지)","artist":"조성모","musicId":"0000090005d280092859","timestamp":"20260216223125","broadcastOffset":1885,"songDuration":247,"talkTimeOffset":369.6,"refinedOffset":539.5,"refinementDelta":169.8,"matchMethod":"name","talkTimeBefore":501,"cumulativeSongDuration":1384,"scriptMentions":[{"timestamp":400.1,"matchType":"artist","matchedTerm":"조성모"},{"timestamp":415.3,"matchType":"artist","matchedTerm":"조성모"},{"timestamp":428.2,"matchType":"artist","matchedTerm":"조성모"},{"timestamp":446.7,"matchType":"artist","matchedTerm":"조성모"},{"timestamp":465.3,"matchType":"artist","matchedTerm":"조성모"},{"timestamp":477.8,"matchType":"artist","matchedTerm":"조성모"},{"timestamp":485.6,"matchType":"artist","matchedTerm":"조성모"},{"timestamp":497.2,"matchType":"artist","matchedTerm":"조성모"},{"timestamp":504.0,"matchType":"artist","matchedTerm":"조성모"},{"timestamp":523.2,"matchType":"artist","matchedTerm":"조성모"}]},{"songTitle":"FOR YOUR SOUL","artist":"조성모","musicId":"0000090005d2800abb0e","timestamp":"20260216223531","broadcastOffset":2131,"songDuration":263,"talkTimeOffset":370.1,"refinedOffset":541.5,"refinementDelta":171.3,"matchMethod":"name","talkTimeBefore":500,"cumulativeSongDuration":1631,"scriptMentions":[{"timestamp":400.1,"matchType":"artist","matchedTerm":"조성모"},{"timestamp":415.3,"matchType":"artist","matchedTerm":"조성모"},{"timestamp":428.2,"matchType":"artist","matchedTerm":"조성모"},{"timestamp":446.7,"matchType":"artist","matchedTerm":"조성모"},{"timestamp":465.3,"matchType":"artist","matchedTerm":"조성모"},{"timestamp":477.8,"matchType":"artist","matchedTerm":"조성모"},{"timestamp":485.6,"matchType":"artist","matchedTerm":"조성모"},{"timestamp":497.2,"matchType":"artist","matchedTerm":"조성모"},{"timestamp":504.0,"matchType":"artist+title","matchedTerm":"조성모+FOR YOUR SOUL"},{"timestamp":523.2,"matchType":"artist","matchedTerm":"조성모"}]},{"songTitle":"불멸의 사랑","artist":"조성모","musicId":"0000090005d2800a8191","timestamp":"20260216223952","broadcastOffset":2392,"songDuration":276,"talkTimeOffset":370.6,"refinedOffset":543.5,"refinementDelta":172.8,"matchMethod":"name","talkTimeBefore":498,"cumulativeSongDuration":1894,"scriptMentions":[{"timestamp":400.1,"matchType":"artist","matchedTerm":"조성모"},{"timestamp":415.3,"matchType":"artist","matchedTerm":"조성모"},{"timestamp":428.2,"matchType":"artist","matchedTerm":"조성모"},{"timestamp":446.7,"matchType":"artist","matchedTerm":"조성모"},{"timestamp":465.3,"matchType":"artist","matchedTerm":"조성모"},{"timestamp":477.8,"matchType":"artist","matchedTerm":"조성모"},{"timestamp":485.6,"matchType":"artist","matchedTerm":"조성모"},{"timestamp":497.2,"matchType":"artist","matchedTerm":"조성모"},{"timestamp":504.0,"matchType":"artist+title","matchedTerm":"조성모+불멸의 사랑"},{"timestamp":523.2,"matchType":"artist","matchedTerm":"조성모"}]},{"songTitle":"다짐","artist":"조성모","musicId":"0000090005d280092c84","timestamp":"20260216224355","broadcastOffset":2635,"songDuration":240,"talkTimeOffset":371.1,"refinedOffset":545.5,"refinementDelta":174.3,"matchMethod":"name","talkTimeBefore":465,"cumulativeSongDuration":2170,"scriptMentions":[{"timestamp":400.1,"matchType":"artist","matchedTerm":"조성모"},{"timestamp":415.3,"matchType":"artist","matchedTerm":"조성모"},{"timestamp":428.2,"matchType":"artist","matchedTerm":"조성모"},{"timestamp":446.7,"matchType":"artist","matchedTerm":"조성모"},{"timestamp":465.3,"matchType":"artist+title","matchedTerm":"조성모+다짐"},{"timestamp":477.8,"matchType":"artist","matchedTerm":"조성모"},{"timestamp":485.6,"matchType":"artist","matchedTerm":"조성모"},{"timestamp":497.2,"matchType":"artist","matchedTerm":"조성모"},{"timestamp":504.0,"matchType":"artist+title","matchedTerm":"조성모+다짐"},{"timestamp":523.2,"matchType":"artist","matchedTerm":"조성모"}]},{"songTitle":"후회","artist":"조성모","musicId":"0000090005d2800b3754","timestamp":"20260216224822","broadcastOffset":2902,"songDuration":267,"talkTimeOffset":371.6,"refinedOffset":547.5,"refinementDelta":175.8,"matchMethod":"name","talkTimeBefore":492,"cumulativeSongDuration":2410,"scriptMentions":[{"timestamp":400.1,"matchType":"artist","matchedTerm":"조성모"},{"timestamp":415.3,"matchType":"artist","matchedTerm":"조성모"},{"timestamp":428.2,"matchType":"artist","matchedTerm":"조성모"},{"timestamp":446.7,"matchType":"artist","matchedTerm":"조성모"},{"timestamp":465.3,"matchType":"artist","matchedTerm":"조성모"},{"timestamp":477.8,"matchType":"artist","matchedTerm":"조성모"},{"timestamp":485.6,"matchType":"artist","matchedTerm":"조성모"},{"timestamp":497.2,"matchType":"artist","matchedTerm":"조성모"},{"timestamp":504.0,"matchType":"artist+title","matchedTerm":"조성모+후회"},{"timestamp":523.2,"matchType":"artist","matchedTerm":"조성모"}]},{"songTitle":"아시나요","artist":"조성모","musicId":"0000090005d280092c92","timestamp":"20260216225452","broadcastOffset":3292,"songDuration":328,"talkTimeOffset":453.7,"refinedOffset":590.1,"refinementDelta":136.4,"matchMethod":"name","talkTimeBefore":615,"cumulativeSongDuration":2677,"scriptMentions":[{"timestamp":400.1,"matchType":"artist","matchedTerm":"조성모"},{"timestamp":415.3,"matchType":"artist","matchedTerm":"조성모"},{"timestamp":428.2,"matchType":"artist","matchedTerm":"조성모"},{"timestamp":446.7,"matchType":"artist","matchedTerm":"조성모"},{"timestamp":465.3,"matchType":"artist+title","matchedTerm":"조성모+아시나요"},{"timestamp":477.8,"matchType":"artist","matchedTerm":"조성모"},{"timestamp":485.6,"matchType":"artist","matchedTerm":"조성모"},{"timestamp":497.2,"matchType":"artist","matchedTerm":"조성모"},{"timestamp":504.0,"matchType":"artist","matchedTerm":"조성모"},{"timestamp":523.2,"matchType":"artist+title","matchedTerm":"조성모+아시나요"}]},{"songTitle":"알고 싶어요","artist":"양파","musicId":"0000090005d2800b0144","timestamp":"20260216230146","broadcastOffset":3706,"songDuration":247,"talkTimeOffset":517.2,"refinedOffset":592.1,"refinementDelta":75.0,"matchMethod":"name","talkTimeBefore":701,"cumulativeSongDuration":3005,"scriptMentions":[{"timestamp":590.1,"matchType":"artist+title","matchedTerm":"양파+알고 싶어요"}]},{"songTitle":"LOVE IS (3+3=0)","artist":"터보","musicId":"0000090005d2800b6d34","timestamp":"20260216230907","broadcastOffset":4147,"songDuration":232,"talkTimeOffset":660.3,"refinedOffset":752.6,"refinementDelta":92.3,"matchMethod":"name","talkTimeBefore":895,"cumulativeSongDuration":3252,"scriptMentions":[{"timestamp":685.0,"matchType":"artist","matchedTerm":"터보"},{"timestamp":694.1,"matchType":"artist","matchedTerm":"터보"},{"timestamp":701.0,"matchType":"artist","matchedTerm":"터보"},{"timestamp":711.3,"matchType":"artist","matchedTerm":"터보"},{"timestamp":722.7,"matchType":"artist","matchedTerm":"터보"},{"timestamp":745.5,"matchType":"artist","matchedTerm":"터보"},{"timestamp":758.0,"matchType":"artist","matchedTerm":"터보"},{"timestamp":762.0,"matchType":"artist","matchedTerm":"터보"}]},{"songTitle":"CYBER  LOVER","artist":"터보","musicId":"0000090005d2800b085b","timestamp":"20260216231231","broadcastOffset":4351,"songDuration":219,"talkTimeOffset":660.8,"refinedOffset":754.6,"refinementDelta":93.8,"matchMethod":"name","talkTimeBefore":867,"cumulativeSongDuration":3484,"scriptMentions":[{"timestamp":685.0,"matchType":"artist","matchedTerm":"터보"},{"timestamp":694.1,"matchType":"artist","matchedTerm":"터보"},{"timestamp":701.0,"matchType":"artist","matchedTerm":"터보"},{"timestamp":711.3,"matchType":"artist","matchedTerm":"터보"},{"timestamp":722.7,"matchType":"artist","matchedTerm":"터보"},{"timestamp":745.5,"matchType":"artist","matchedTerm":"터보"},{"timestamp":758.0,"matchType":"artist","matchedTerm":"터보"},{"timestamp":762.0,"matchType":"artist+title","matchedTerm":"터보+CYBER  LOVER"}]},{"songTitle":"애인이 생겼어요","artist":"터보","musicId":"0000090005d2800b363f","timestamp":"20260216231613","broadcastOffset":4573,"songDuration":216,"talkTimeOffset":661.3,"refinedOffset":756.6,"refinementDelta":95.3,"matchMethod":"name","talkTimeBefore":870,"cumulativeSongDuration":3703,"scriptMentions":[{"timestamp":685.0,"matchType":"artist","matchedTerm":"터보"},{"timestamp":694.1,"matchType":"artist","matchedTerm":"터보"},{"timestamp":701.0,"matchType":"artist","matchedTerm":"터보"},{"timestamp":711.3,"matchType":"artist","matchedTerm":"터보"},{"timestamp":722.7,"matchType":"artist","matchedTerm":"터보"},{"timestamp":745.5,"matchType":"artist","matchedTerm":"터보"},{"timestamp":758.0,"matchType":"artist","matchedTerm":"터보"},{"timestamp":762.0,"matchType":"artist+title","matchedTerm":"터보+애인이 생겼어요"}]},{"songTitle":"TONIGHT","artist":"터보","musicId":"0000090005d2800b085a","timestamp":"20260216232019","broadcastOffset":4819,"songDuration":272,"talkTimeOffset":664.0,"refinedOffset":758.6,"refinementDelta":94.7,"matchMethod":"name","talkTimeBefore":900,"cumulativeSongDuration":3919,"scriptMentions":[{"timestamp":685.0,"matchType":"artist","matchedTerm":"터보"},{"timestamp":694.1,"matchType":"artist","matchedTerm":"터보"},{"timestamp":701.0,"matchType":"artist","matchedTerm":"터보"},{"timestamp":711.3,"matchType":"artist","matchedTerm":"터보"},{"timestamp":722.7,"matchType":"artist","matchedTerm":"터보"},{"timestamp":745.5,"matchType":"artist","matchedTerm":"터보"},{"timestamp":758.0,"matchType":"artist","matchedTerm":"터보"},{"timestamp":762.0,"matchType":"artist","matchedTerm":"터보"}]},{"songTitle":"회상(DECEMBER)","artist":"터보","musicId":"0000090005d28012e455","timestamp":"20260216232422","broadcastOffset":5062,"songDuration":257,"talkTimeOffset":664.5,"refinedOffset":760.6,"refinementDelta":96.2,"matchMethod":"name","talkTimeBefore":871,"cumulativeSongDuration":4191,"scriptMentions":[{"timestamp":685.0,"matchType":"artist","matchedTerm":"터보"},{"timestamp":694.1,"matchType":"artist","matchedTerm":"터보"},{"timestamp":701.0,"matchType":"artist","matchedTerm":"터보"},{"timestamp":711.3,"matchType":"artist","matchedTerm":"터보"},{"timestamp":722.7,"matchType":"artist","matchedTerm":"터보"},{"timestamp":745.5,"matchType":"artist","matchedTerm":"터보"},{"timestamp":758.0,"matchType":"artist","matchedTerm":"터보"},{"timestamp":762.0,"matchType":"artist+title","matchedTerm":"터보+회상"}]},{"songTitle":"애상 (MR)","artist":"COOL","musicId":"0000090005d28012bc4c","timestamp":"20260216233046","broadcastOffset":5446,"songDuration":0,"talkTimeOffset":736.3,"refinedOffset":762.6,"refinementDelta":0,"matchMethod":"talk_time","talkTimeBefore":998,"cumulativeSongDuration":4448},{"songTitle":"운명","artist":"COOL","musicId":"0000090005d280072539","timestamp":"20260216233446","broadcastOffset":5686,"songDuration":225,"talkTimeOffset":913.3,"refinedOffset":913.3,"refinementDelta":0,"matchMethod":"talk_time","talkTimeBefore":1238,"cumulativeSongDuration":4448},{"songTitle":"해변의 여인","artist":"COOL","musicId":"0000090005d28010a5f9","timestamp":"20260216233846","broadcastOffset":5926,"songDuration":220,"talkTimeOffset":924.4,"refinedOffset":881.2,"refinementDelta":43.2,"matchMethod":"name","talkTimeBefore":1253,"cumulativeSongDuration":4673,"scriptMentions":[{"timestamp":844.9,"matchType":"title","matchedTerm":"해변의 여인"},{"timestamp":863.6,"matchType":"title","matchedTerm":"해변의 여인"}]},{"songTitle":"JUMPO MAMBO","artist":"COOL","musicId":"0000090005d2807dabea","timestamp":"20260216234204","broadcastOffset":6124,"songDuration":225,"talkTimeOffset":924.9,"refinedOffset":924.9,"refinementDelta":0,"matchMethod":"talk_time","talkTimeBefore":1231,"cumulativeSongDuration":4893},{"songTitle":"해석남녀","artist":"COOL","musicId":"0000090005d2800ae8cc","timestamp":"20260216234552","broadcastOffset":6352,"songDuration":204,"talkTimeOffset":925.4,"refinedOffset":926.9,"refinementDelta":0,"matchMethod":"talk_time","talkTimeBefore":1234,"cumulativeSongDuration":5118},{"songTitle":"이 여름 SUMMER","artist":"COOL","musicId":"0000090005d280df4bae","timestamp":"20260216234843","broadcastOffset":6523,"songDuration":234,"talkTimeOffset":925.9,"refinedOffset":928.9,"refinementDelta":0,"matchMethod":"talk_time","talkTimeBefore":1201,"cumulativeSongDuration":5322},{"songTitle":"PERHAPS LOVE (사랑인가요)","artist":"제이Ψ하울","musicId":"20060127172701092046","timestamp":"20260216235443","broadcastOffset":6883,"songDuration":275,"talkTimeOffset":979.0,"refinedOffset":966.4,"refinementDelta":12.6,"matchMethod":"name","talkTimeBefore":1327,"cumulativeSongDuration":5556,"scriptMentions":[{"timestamp":958.3,"matchType":"title","matchedTerm":"사랑인가요"}]}],"sentenceEndPoints":[21.75,68.79,83.27,93.47,112.12,125.04,140.85,153.52,200.79,214.85,224.2,249.57,256.62,281.57,288.56,294.21,306.2,318.57,340.02,347.19,422.09,426.63,463.68,483.71,495.75,539.46,592.9,676.51,699.88,709.92,732.42,744.24,821.28,830.92,841.37,856.71,871.5,957.12]}